guiboweb
